smartinspect/__init__.py
smartinspect/configuration.py
smartinspect/configuration_timer.py
smartinspect/si_auto.py
smartinspect/smartinspect.py
smartinspect/common/__init__.py
smartinspect/common/clock.py
smartinspect/common/exceptions.py
smartinspect/common/file_helper.py
smartinspect/common/file_path.py
smartinspect/common/file_rotate.py
smartinspect/common/file_rotater.py
smartinspect/common/level.py
smartinspect/common/locked_dictionary.py
smartinspect/common/locked_set.py
smartinspect/common/lookup_table.py
smartinspect/common/pattern_parser.py
smartinspect/common/protocol_command.py
smartinspect/common/source_id.py
smartinspect/common/viewer_id.py
smartinspect/common/color/__init__.py
smartinspect/common/color/color.py
smartinspect/common/color/rgbacolor.py
smartinspect/common/context/__init__.py
smartinspect/common/context/binary_context.py
smartinspect/common/context/binary_viewer_context.py
smartinspect/common/context/data_viewer_context.py
smartinspect/common/context/inspector_viewer_context.py
smartinspect/common/context/list_viewer_context.py
smartinspect/common/context/tableviewercontext.py
smartinspect/common/context/text_context.py
smartinspect/common/context/value_list_viewer_context.py
smartinspect/common/context/viewer_context.py
smartinspect/common/events/__init__.py
smartinspect/common/events/connections_parser_event.py
smartinspect/common/events/control_command_event.py
smartinspect/common/events/error_event.py
smartinspect/common/events/filter_event.py
smartinspect/common/events/log_entry_event.py
smartinspect/common/events/process_flow_event.py
smartinspect/common/events/watch_event.py
smartinspect/common/listener/__init__.py
smartinspect/common/listener/protocol_listener.py
smartinspect/common/listener/smartinspect_listener.py
smartinspect/common/tokens/__init__.py
smartinspect/common/tokens/token_abc.py
smartinspect/common/tokens/token_factory.py
smartinspect/common/tokens/tokens.py
smartinspect/connections/__init__.py
smartinspect_py-4.0.5.dist-info/METADATA
smartinspect_py-4.0.5.dist-info/WHEEL
smartinspect_py-4.0.5.dist-info/top_level.txt
smartinspect_py-4.0.5.dist-info/RECORD
