Metadata-Version: 2.4
Name: smartinspect-py
Version: 4.0.5
Summary: Client library to integrate SmartInspect logging into Python applications.
Author-email: Sergey Udachin <sergey.udachin@code-partners.com>
Maintainer-email: Sergey Zhukov <sergey@code-partners.com>
License: MIT License
Project-URL: Homepage, https://code-partners.com/offerings/smartinspect/
Project-URL: Issues, https://github.com/Code-Partners/smartinspect-python-library/issues
Keywords: smartinspect,logging
Classifier: Programming Language :: Python :: 3
Classifier: Operating System :: OS Independent
Classifier: Development Status :: 5 - Production/Stable
Classifier: Intended Audience :: Developers
Classifier: License :: OSI Approved :: MIT License
Classifier: Natural Language :: English
Classifier: Topic :: System :: Logging
Classifier: Topic :: Software Development :: Libraries :: Python Modules
Requires-Python: >=3.7
Requires-Dist: cryptography>=42.0.5
